erexplain/__init__.py
erexplain/pattern_discovery.py
erexplain/triangles_method.py
erexplain-0.1.2.dist-info/LICENSE
erexplain-0.1.2.dist-info/LICENSE.txt
erexplain-0.1.2.dist-info/METADATA
erexplain-0.1.2.dist-info/WHEEL
erexplain-0.1.2.dist-info/top_level.txt
erexplain-0.1.2.dist-info/RECORD
