Metadata-Version: 2.1
Name: erexplain
Version: 0.1.2
Summary: library to explain models for Entity Resolution
Home-page: https://github.com/vincenzomartello/ERExplain.git
Author: Vincenzo Martello
Author-email: v.martello@libero.it
License: UNKNOWN
Download-URL: https://github.com/vincenzomartello/ERExplain/archive/0.1.2.tar.gz
Platform: UNKNOWN
Classifier: Programming Language :: Python :: 3
Classifier: License :: OSI Approved :: Apache Software License
Classifier: Operating System :: OS Independent
Classifier: Topic :: Scientific/Engineering :: Artificial Intelligence
Requires-Python: >=3.6
Requires-Dist: pandas
Requires-Dist: numpy
Requires-Dist: tqdm
Requires-Dist: mlxtend (>=0.17.2)
